deeplearn/__init__.py
test/__init__.py
rec_model_pipeline-0.0.1.dist-info/METADATA
rec_model_pipeline-0.0.1.dist-info/WHEEL
rec_model_pipeline-0.0.1.dist-info/top_level.txt
rec_model_pipeline-0.0.1.dist-info/RECORD
