Metadata-Version: 2.1
Name: rec-model-pipeline
Version: 0.0.1
Summary: common_rec_pipeline_keras
Home-page: https://git.woa.com/gcd/game_indust_v3/tree/master/rcmd_models/common_rec_pipeline_keras
Author: hayzheng
Author-email: zhenghangcx@163.com
License: MIT
